autoroblox/__init__.py
autoroblox-1.1.2.dist-info/LICENSE.txt
autoroblox-1.1.2.dist-info/METADATA
autoroblox-1.1.2.dist-info/WHEEL
autoroblox-1.1.2.dist-info/top_level.txt
autoroblox-1.1.2.dist-info/RECORD
