Metadata-Version: 2.1
Name: autoroblox
Version: 1.1.2
Summary: AutoRoblox is a library offering tools for automating Roblox-related gameplay.
Home-page: https://github.com/autoRobloxProject/AutoRoblox
Author: AutoRoblox Project
Author-email: contact.autoroblox@gmail.com
Classifier: Programming Language :: Python :: 3
Classifier: License :: Other/Proprietary License
Classifier: Operating System :: Microsoft :: Windows
Classifier: Operating System :: OS Independent
Requires-Python: >=3.6
License-File: LICENSE.txt
Requires-Dist: pynput
Requires-Dist: keyboard
Requires-Dist: requests
